streamlit_openai/__init__.py
streamlit_openai/__main__.py
streamlit_openai/chat.py
streamlit_openai/utils.py
streamlit_openai/version.py
streamlit_openai-0.1.4.dist-info/LICENSE
streamlit_openai-0.1.4.dist-info/METADATA
streamlit_openai-0.1.4.dist-info/WHEEL
streamlit_openai-0.1.4.dist-info/entry_points.txt
streamlit_openai-0.1.4.dist-info/top_level.txt
streamlit_openai-0.1.4.dist-info/RECORD
