Metadata-Version: 2.1
Name: streamlit-openai
Version: 0.1.4
Summary: Build AI chatbots with Streamlit and OpenAI
Home-page: https://github.com/sbslee/streamlit-openai
Author: Seung-been "Steven" Lee
Author-email: sbstevenlee@gmail.com
License: MIT
Platform: UNKNOWN
